pyvkpns/__init__.py
pyvkpns/client.py
pyvkpns/credentials.py
pyvkpns/exceptions.py
pyvkpns/http_client.py
pyvkpns/message/model.py
pyvkpns/message/preparer.py
pyvkpns/utils/__init__.py
pyvkpns/utils/empty_remover.py
pyvkpns/utils/none_remover.py
pyvkpns/validator/__init__.py
pyvkpns/validator/response_validator.py
pyvkpns-0.1.2.dist-info/METADATA
pyvkpns-0.1.2.dist-info/WHEEL
pyvkpns-0.1.2.dist-info/licenses/LICENSE
pyvkpns-0.1.2.dist-info/RECORD
